<Properties StartupConfiguration="{5D566141-5B17-4B45-89DB-206454D622E1}|Default">
  <MonoDevelop.Ide.Workbench ActiveDocument="Main_Program/Module1.vb">
    <Files>
      <File FileName="Main_Program/Module1.vb" Line="37" Column="1" />
    </Files>
    <Pads>
      <Pad Id="ProjectPad">
        <State name="__root__">
          <Node name="Main_Program" expanded="True">
            <Node name="Main_Program" expanded="True">
              <Node name="Module1.vb" selected="True" />
            </Node>
          </Node>
        </State>
      </Pad>
      <Pad Id="MonoDevelop.Debugger.WatchPad">
        <State />
      </Pad>
    </Pads>
  </MonoDevelop.Ide.Workbench>
  <MonoDevelop.Ide.ItemProperties.Main__Program PreferredExecutionTarget="MonoDevelop.Default" />
  <MonoDevelop.Ide.DebuggingService.PinnedWatches />
  <MonoDevelop.Ide.Workspace ActiveConfiguration="Debug" />
  <MonoDevelop.Ide.DebuggingService.Breakpoints>
    <BreakpointStore />
  </MonoDevelop.Ide.DebuggingService.Breakpoints>
  <MultiItemStartupConfigurations />
</Properties>